pyado/__init__.py
pyado/api_call.py
pyado/build.py
pyado/pipeline.py
pyado/project.py
pyado/pull_request.py
pyado/py.typed
pyado/repository.py
pyado/variable_group.py
pyado/work_item.py
pyado-0.1.17.dist-info/WHEEL
pyado-0.1.17.dist-info/METADATA
pyado-0.1.17.dist-info/RECORD
