Metadata-Version: 2.3
Name: pyado
Version: 0.1.17
Summary: Add your description here
Author: Fred Stober
Author-email: Fred Stober <pyado@fredstober.de>
Requires-Dist: pydantic>=2.11.7
Requires-Dist: requests>=2.32.2
Requires-Python: >=3.11
